hrw/__init__.py
hrw/functions.py
hrw-0.2.0.dist-info/METADATA
hrw-0.2.0.dist-info/WHEEL
hrw-0.2.0.dist-info/licenses/license
hrw-0.2.0.dist-info/RECORD
