Metadata-Version: 2.1
Name: hrw
Version: 0.2.0
Summary: Highest random weight/rendezvous hashing for load balancing between replicas.
Project-URL: Homepage, https://github.com/k98kurz/hrw
Project-URL: Bug Tracker, https://github.com/k98kurz/hrw/issues
Author-email: k98kurz <k98kurz@gmail.com>
License-File: license
Classifier: Development Status :: 4 - Beta
Classifier: License :: OSI Approved :: ISC License (ISCL)
Classifier: Operating System :: OS Independent
Classifier: Programming Language :: Python :: 3
Classifier: Topic :: System :: Distributed Computing
Requires-Python: >=3.7
